README.md
setup.cfg
setup.py
s_exp_parser.egg-info/PKG-INFO
s_exp_parser.egg-info/SOURCES.txt
s_exp_parser.egg-info/dependency_links.txt
s_exp_parser.egg-info/requires.txt
s_exp_parser.egg-info/top_level.txt
s_expression_parser/__init__.py
s_expression_parser/configs.py
s_expression_parser/lexer.py
s_expression_parser/parser.py
s_expression_parser/renderer.py
tests/__init__.py
tests/test_lexer.py
tests/test_parser.py
tests/test_renderer.py